RadSI.py
RadSI-1.0.7.dist-info/LICENSE
RadSI-1.0.7.dist-info/METADATA
RadSI-1.0.7.dist-info/WHEEL
RadSI-1.0.7.dist-info/entry_points.txt
RadSI-1.0.7.dist-info/top_level.txt
RadSI-1.0.7.dist-info/RECORD
