Metadata-Version: 2.1
Name: RadSI
Version: 1.0.7
Summary: A CLI radiation source inventory
Home-page: https://github.com/matthewdurbin/RadSI
Author: Matthew Durbin
Author-email: mud370@psu.edu
License: UNKNOWN
Platform: UNKNOWN
Classifier: Programming Language :: Python :: 3
Classifier: License :: OSI Approved :: MIT License
Classifier: Operating System :: OS Independent
Requires-Python: >=3.5
Requires-Dist: setuptools
Requires-Dist: pandas
Requires-Dist: numpy
Requires-Dist: fire
Requires-Dist: matplotlib
